[{
  "logId" : 27632375938,
  "dateOfSleep" : "2020-06-14",
  "startTime" : "2020-06-14T16:37:00.000",
  "endTime" : "2020-06-14T17:54:00.000",
  "duration" : 4620000,
  "minutesToFallAsleep" : 0,
  "minutesAsleep" : 65,
  "minutesAwake" : 12,
  "minutesAfterWakeup" : 0,
  "timeInBed" : 77,
  "efficiency" : 84,
  "type" : "classic",
  "infoCode" : 2,
  "levels" : {
    "summary" : {
      "restless" : {
        "count" : 5,
        "minutes" : 9
      },
      "awake" : {
        "count" : 2,
        "minutes" : 3
      },
      "asleep" : {
        "count" : 0,
        "minutes" : 65
      }
    },
    "data" : [{
      "dateTime" : "2020-06-14T16:37:00.000",
      "level" : "asleep",
      "seconds" : 480
    },{
      "dateTime" : "2020-06-14T16:45:00.000",
      "level" : "restless",
      "seconds" : 60
    },{
      "dateTime" : "2020-06-14T16:46:00.000",
      "level" : "awake",
      "seconds" : 120
    },{
      "dateTime" : "2020-06-14T16:48:00.000",
      "level" : "restless",
      "seconds" : 240
    },{
      "dateTime" : "2020-06-14T16:52:00.000",
      "level" : "asleep",
      "seconds" : 420
    },{
      "dateTime" : "2020-06-14T16:59:00.000",
      "level" : "restless",
      "seconds" : 120
    },{
      "dateTime" : "2020-06-14T17:01:00.000",
      "level" : "asleep",
      "seconds" : 2880
    },{
      "dateTime" : "2020-06-14T17:49:00.000",
      "level" : "restless",
      "seconds" : 60
    },{
      "dateTime" : "2020-06-14T17:50:00.000",
      "level" : "awake",
      "seconds" : 60
    },{
      "dateTime" : "2020-06-14T17:51:00.000",
      "level" : "restless",
      "seconds" : 60
    },{
      "dateTime" : "2020-06-14T17:52:00.000",
      "level" : "asleep",
      "seconds" : 120
    }]
  },
  "mainSleep" : false
},{
  "logId" : 27617587547,
  "dateOfSleep" : "2020-06-14",
  "startTime" : "2020-06-13T22:34:30.000",
  "endTime" : "2020-06-14T08:35:30.000",
  "duration" : 36060000,
  "minutesToFallAsleep" : 0,
  "minutesAsleep" : 533,
  "minutesAwake" : 68,
  "minutesAfterWakeup" : 0,
  "timeInBed" : 601,
  "efficiency" : 96,
  "type" : "stages",
  "infoCode" : 0,
  "levels" : {
    "summary" : {
      "deep" : {
        "count" : 6,
        "minutes" : 76,
        "thirtyDayAvgMinutes" : 0
      },
      "wake" : {
        "count" : 40,
        "minutes" : 68,
        "thirtyDayAvgMinutes" : 0
      },
      "light" : {
        "count" : 41,
        "minutes" : 367,
        "thirtyDayAvgMinutes" : 0
      },
      "rem" : {
        "count" : 11,
        "minutes" : 90,
        "thirtyDayAvgMinutes" : 0
      }
    },
    "data" : [{
      "dateTime" : "2020-06-13T22:34:30.000",
      "level" : "wake",
      "seconds" : 330
    },{
      "dateTime" : "2020-06-13T22:40:00.000",
      "level" : "light",
      "seconds" : 900
    },{
      "dateTime" : "2020-06-13T22:55:00.000",
      "level" : "deep",
      "seconds" : 2100
    },{
      "dateTime" : "2020-06-13T23:30:00.000",
      "level" : "light",
      "seconds" : 4620
    },{
      "dateTime" : "2020-06-14T00:47:00.000",
      "level" : "deep",
      "seconds" : 960
    },{
      "dateTime" : "2020-06-14T01:03:00.000",
      "level" : "light",
      "seconds" : 2430
    },{
      "dateTime" : "2020-06-14T01:43:30.000",
      "level" : "deep",
      "seconds" : 510
    },{
      "dateTime" : "2020-06-14T01:52:00.000",
      "level" : "light",
      "seconds" : 900
    },{
      "dateTime" : "2020-06-14T02:07:00.000",
      "level" : "deep",
      "seconds" : 450
    },{
      "dateTime" : "2020-06-14T02:14:30.000",
      "level" : "light",
      "seconds" : 1440
    },{
      "dateTime" : "2020-06-14T02:38:30.000",
      "level" : "rem",
      "seconds" : 1320
    },{
      "dateTime" : "2020-06-14T03:00:30.000",
      "level" : "light",
      "seconds" : 2640
    },{
      "dateTime" : "2020-06-14T03:44:30.000",
      "level" : "deep",
      "seconds" : 360
    },{
      "dateTime" : "2020-06-14T03:50:30.000",
      "level" : "wake",
      "seconds" : 210
    },{
      "dateTime" : "2020-06-14T03:54:00.000",
      "level" : "light",
      "seconds" : 570
    },{
      "dateTime" : "2020-06-14T04:03:30.000",
      "level" : "rem",
      "seconds" : 330
    },{
      "dateTime" : "2020-06-14T04:09:00.000",
      "level" : "light",
      "seconds" : 480
    },{
      "dateTime" : "2020-06-14T04:17:00.000",
      "level" : "rem",
      "seconds" : 690
    },{
      "dateTime" : "2020-06-14T04:28:30.000",
      "level" : "light",
      "seconds" : 4110
    },{
      "dateTime" : "2020-06-14T05:37:00.000",
      "level" : "rem",
      "seconds" : 1260
    },{
      "dateTime" : "2020-06-14T05:58:00.000",
      "level" : "light",
      "seconds" : 2190
    },{
      "dateTime" : "2020-06-14T06:34:30.000",
      "level" : "deep",
      "seconds" : 420
    },{
      "dateTime" : "2020-06-14T06:41:30.000",
      "level" : "light",
      "seconds" : 510
    },{
      "dateTime" : "2020-06-14T06:50:00.000",
      "level" : "rem",
      "seconds" : 1320
    },{
      "dateTime" : "2020-06-14T07:12:00.000",
      "level" : "light",
      "seconds" : 60
    },{
      "dateTime" : "2020-06-14T07:13:00.000",
      "level" : "wake",
      "seconds" : 210
    },{
      "dateTime" : "2020-06-14T07:16:30.000",
      "level" : "light",
      "seconds" : 750
    },{
      "dateTime" : "2020-06-14T07:29:00.000",
      "level" : "wake",
      "seconds" : 300
    },{
      "dateTime" : "2020-06-14T07:34:00.000",
      "level" : "light",
      "seconds" : 1590
    },{
      "dateTime" : "2020-06-14T08:00:30.000",
      "level" : "rem",
      "seconds" : 300
    },{
      "dateTime" : "2020-06-14T08:05:30.000",
      "level" : "light",
      "seconds" : 630
    },{
      "dateTime" : "2020-06-14T08:16:00.000",
      "level" : "rem",
      "seconds" : 300
    },{
      "dateTime" : "2020-06-14T08:21:00.000",
      "level" : "wake",
      "seconds" : 870
    }],
    "shortData" : [{
      "dateTime" : "2020-06-13T22:42:00.000",
      "level" : "wake",
      "seconds" : 90
    },{
      "dateTime" : "2020-06-13T23:28:00.000",
      "level" : "wake",
      "seconds" : 120
    },{
      "dateTime" : "2020-06-13T23:32:00.000",
      "level" : "wake",
      "seconds" : 120
    },{
      "dateTime" : "2020-06-13T23:45:30.000",
      "level" : "wake",
      "seconds" : 30
    },{
      "dateTime" : "2020-06-13T23:47:30.000",
      "level" : "wake",
      "seconds" : 30
    },{
      "dateTime" : "2020-06-13T23:55:00.000",
      "level" : "wake",
      "seconds" : 30
    },{
      "dateTime" : "2020-06-14T00:19:00.000",
      "level" : "wake",
      "seconds" : 30
    },{
      "dateTime" : "2020-06-14T00:22:30.000",
      "level" : "wake",
      "seconds" : 60
    },{
      "dateTime" : "2020-06-14T01:03:00.000",
      "level" : "wake",
      "seconds" : 90
    },{
      "dateTime" : "2020-06-14T01:25:30.000",
      "level" : "wake",
      "seconds" : 60
    },{
      "dateTime" : "2020-06-14T01:53:30.000",
      "level" : "wake",
      "seconds" : 60
    },{
      "dateTime" : "2020-06-14T02:13:00.000",
      "level" : "wake",
      "seconds" : 90
    },{
      "dateTime" : "2020-06-14T02:20:30.000",
      "level" : "wake",
      "seconds" : 90
    },{
      "dateTime" : "2020-06-14T02:43:00.000",
      "level" : "wake",
      "seconds" : 30
    },{
      "dateTime" : "2020-06-14T02:48:00.000",
      "level" : "wake",
      "seconds" : 60
    },{
      "dateTime" : "2020-06-14T03:03:00.000",
      "level" : "wake",
      "seconds" : 30
    },{
      "dateTime" : "2020-06-14T03:05:00.000",
      "level" : "wake",
      "seconds" : 30
    },{
      "dateTime" : "2020-06-14T03:07:00.000",
      "level" : "wake",
      "seconds" : 30
    },{
      "dateTime" : "2020-06-14T03:19:30.000",
      "level" : "wake",
      "seconds" : 30
    },{
      "dateTime" : "2020-06-14T04:09:30.000",
      "level" : "wake",
      "seconds" : 150
    },{
      "dateTime" : "2020-06-14T04:13:30.000",
      "level" : "wake",
      "seconds" : 150
    },{
      "dateTime" : "2020-06-14T04:29:00.000",
      "level" : "wake",
      "seconds" : 90
    },{
      "dateTime" : "2020-06-14T04:35:30.000",
      "level" : "wake",
      "seconds" : 90
    },{
      "dateTime" : "2020-06-14T04:38:30.000",
      "level" : "wake",
      "seconds" : 60
    },{
      "dateTime" : "2020-06-14T05:16:30.000",
      "level" : "wake",
      "seconds" : 30
    },{
      "dateTime" : "2020-06-14T05:27:00.000",
      "level" : "wake",
      "seconds" : 60
    },{
      "dateTime" : "2020-06-14T05:34:30.000",
      "level" : "wake",
      "seconds" : 60
    },{
      "dateTime" : "2020-06-14T05:53:00.000",
      "level" : "wake",
      "seconds" : 30
    },{
      "dateTime" : "2020-06-14T05:59:30.000",
      "level" : "wake",
      "seconds" : 30
    },{
      "dateTime" : "2020-06-14T06:09:00.000",
      "level" : "wake",
      "seconds" : 30
    },{
      "dateTime" : "2020-06-14T06:41:30.000",
      "level" : "wake",
      "seconds" : 60
    },{
      "dateTime" : "2020-06-14T07:04:30.000",
      "level" : "wake",
      "seconds" : 30
    },{
      "dateTime" : "2020-06-14T07:18:00.000",
      "level" : "wake",
      "seconds" : 60
    },{
      "dateTime" : "2020-06-14T07:22:00.000",
      "level" : "wake",
      "seconds" : 60
    },{
      "dateTime" : "2020-06-14T07:59:30.000",
      "level" : "wake",
      "seconds" : 60
    }]
  },
  "mainSleep" : true
}]