[{
  "dateTime" : "05/21/19 00:00:00",
  "value" : "308"
},{
  "dateTime" : "05/22/19 00:00:00",
  "value" : "168"
},{
  "dateTime" : "05/23/19 00:00:00",
  "value" : "227"
},{
  "dateTime" : "05/24/19 00:00:00",
  "value" : "203"
},{
  "dateTime" : "05/25/19 00:00:00",
  "value" : "175"
},{
  "dateTime" : "05/26/19 00:00:00",
  "value" : "192"
},{
  "dateTime" : "05/27/19 00:00:00",
  "value" : "245"
},{
  "dateTime" : "05/28/19 00:00:00",
  "value" : "280"
},{
  "dateTime" : "05/29/19 00:00:00",
  "value" : "325"
},{
  "dateTime" : "05/30/19 00:00:00",
  "value" : "182"
},{
  "dateTime" : "05/31/19 00:00:00",
  "value" : "152"
},{
  "dateTime" : "06/01/19 00:00:00",
  "value" : "313"
},{
  "dateTime" : "06/02/19 00:00:00",
  "value" : "257"
},{
  "dateTime" : "06/03/19 00:00:00",
  "value" : "274"
},{
  "dateTime" : "06/04/19 00:00:00",
  "value" : "303"
},{
  "dateTime" : "06/05/19 00:00:00",
  "value" : "102"
},{
  "dateTime" : "06/06/19 00:00:00",
  "value" : "239"
},{
  "dateTime" : "06/07/19 00:00:00",
  "value" : "215"
},{
  "dateTime" : "06/08/19 00:00:00",
  "value" : "289"
},{
  "dateTime" : "06/09/19 00:00:00",
  "value" : "162"
},{
  "dateTime" : "06/10/19 00:00:00",
  "value" : "183"
},{
  "dateTime" : "06/11/19 00:00:00",
  "value" : "162"
},{
  "dateTime" : "06/12/19 00:00:00",
  "value" : "167"
},{
  "dateTime" : "06/13/19 00:00:00",
  "value" : "158"
},{
  "dateTime" : "06/14/19 00:00:00",
  "value" : "208"
},{
  "dateTime" : "06/15/19 00:00:00",
  "value" : "164"
},{
  "dateTime" : "06/16/19 00:00:00",
  "value" : "64"
},{
  "dateTime" : "06/17/19 00:00:00",
  "value" : "146"
},{
  "dateTime" : "06/18/19 00:00:00",
  "value" : "152"
},{
  "dateTime" : "06/19/19 00:00:00",
  "value" : "221"
}]